README.md
pyproject.toml
setup.cfg
setup.py
examples/__init__.py
examples/concertbot/__init__.py
examples/concertbot/actions.py
examples/knowledgebasebot/__init__.py
examples/knowledgebasebot/actions.py
examples/nlg_server/__init__.py
examples/nlg_server/nlg_server.py
examples/reminderbot/__init__.py
examples/reminderbot/actions.py
examples/restaurantbot/__init__.py
examples/restaurantbot/actions.py
examples/restaurantbot/policy.py
examples/restaurantbot/run.py
nlu_bf/__init__.py
nlu_bf/__main__.py
nlu_bf/constants.py
nlu_bf/data.py
nlu_bf/exceptions.py
nlu_bf/from rasa.nlu.components import Componen.py
nlu_bf/jupyter.py
nlu_bf/model.py
nlu_bf/run.py
nlu_bf/server.py
nlu_bf/test.py
nlu_bf/train.py
nlu_bf/validator.py
nlu_bf/version.py
nlu_bf.egg-info/PKG-INFO
nlu_bf.egg-info/SOURCES.txt
nlu_bf.egg-info/dependency_links.txt
nlu_bf.egg-info/entry_points.txt
nlu_bf.egg-info/requires.txt
nlu_bf.egg-info/top_level.txt
nlu_bf/cli/__init__.py
nlu_bf/cli/data.py
nlu_bf/cli/export.py
nlu_bf/cli/interactive.py
nlu_bf/cli/run.py
nlu_bf/cli/scaffold.py
nlu_bf/cli/shell.py
nlu_bf/cli/test.py
nlu_bf/cli/train.py
nlu_bf/cli/utils.py
nlu_bf/cli/visualize.py
nlu_bf/cli/x.py
nlu_bf/cli/arguments/__init__.py
nlu_bf/cli/arguments/data.py
nlu_bf/cli/arguments/default_arguments.py
nlu_bf/cli/arguments/export.py
nlu_bf/cli/arguments/interactive.py
nlu_bf/cli/arguments/run.py
nlu_bf/cli/arguments/shell.py
nlu_bf/cli/arguments/test.py
nlu_bf/cli/arguments/train.py
nlu_bf/cli/arguments/visualize.py
nlu_bf/cli/arguments/x.py
nlu_bf/cli/initial_project/__init__.py
nlu_bf/cli/initial_project/actions.py
nlu_bf/core/__init__.py
nlu_bf/core/agent.py
nlu_bf/core/config.py
nlu_bf/core/constants.py
nlu_bf/core/conversation.py
nlu_bf/core/domain.py
nlu_bf/core/evaluate.py
nlu_bf/core/exceptions.py
nlu_bf/core/exporter.py
nlu_bf/core/featurizers.py
nlu_bf/core/interpreter.py
nlu_bf/core/jobs.py
nlu_bf/core/lock.py
nlu_bf/core/lock_store.py
nlu_bf/core/processor.py
nlu_bf/core/registry.py
nlu_bf/core/restore.py
nlu_bf/core/run.py
nlu_bf/core/slots.py
nlu_bf/core/test.py
nlu_bf/core/tracker_store.py
nlu_bf/core/trackers.py
nlu_bf/core/train.py
nlu_bf/core/utils.py
